jupyterlab_downloadfolder/__init__.py
jupyterlab_downloadfolder/_version.py
jupyterlab_downloadfolder/handler.py
jupyterlab_downloadfolder-0.1.1.data/data/etc/jupyter/jupyter_notebook_config.d/jupyterlab_downloadfolder.json
jupyterlab_downloadfolder-0.1.1.dist-info/LICENSE.txt
jupyterlab_downloadfolder-0.1.1.dist-info/METADATA
jupyterlab_downloadfolder-0.1.1.dist-info/WHEEL
jupyterlab_downloadfolder-0.1.1.dist-info/top_level.txt
jupyterlab_downloadfolder-0.1.1.dist-info/RECORD
