Metadata-Version: 2.1
Name: jupyterlab-downloadfolder
Version: 0.1.1
Summary: Plugin JupyterLab for Downloading a folder as archive
Home-page: https://github.com/fcollonval/jupyterlab-download-folder
Author: Frederic Collonval
Author-email: fcollonval@gmail.com
License: MIT
Keywords: jupyterlab
Platform: UNKNOWN
Classifier: Intended Audience :: Developers
Classifier: Intended Audience :: System Administrators
Classifier: Intended Audience :: Science/Research
Classifier: Programming Language :: Python
Classifier: Programming Language :: Python :: 3
Requires-Python: >=3.5
Requires-Dist: jupyterlab
